.gitignore
LICENSE
README.md
build.sh
config.cfg
setup.py
test.py
upload.sh
bitfieldpy/__init__.py
bitfieldpy/bitfieldpy.py
bitfieldpy/version.py
bitfieldpy.egg-info/PKG-INFO
bitfieldpy.egg-info/SOURCES.txt
bitfieldpy.egg-info/dependency_links.txt
bitfieldpy.egg-info/entry_points.txt
bitfieldpy.egg-info/requires.txt
bitfieldpy.egg-info/top_level.txt
tests/.gitignore
tests/Makefile
tests/.circleci/config.yml
tests/data/bitfields/bits.json
tests/images/bits.svg
tests/markdown/TITLE.md
tests/markdown/config.yaml