Metadata-Version: 1.1
Name: bitfieldpy
Version: 0.0.9
Summary: Python3 porting of bitfield(https://github.com/drom/bitfield) with all respect
Home-page: https://github.com/K4zuki/bitfieldpy
Author: Kazuki Yamamoto
Author-email: k.yamamoto.08136891@gmail.com
License: UNKNOWN
Keywords: svg
Platform: UNKNOWN
Classifier: Development Status :: 3 - Alpha
Classifier: Intended Audience :: Developers
Classifier: Topic :: Software Development :: Build Tools
Classifier: License :: OSI Approved :: MIT License
Classifier: Programming Language :: Python :: 3
Classifier: Programming Language :: Python :: 3.5
Classifier: Programming Language :: Python :: 3.6
